sparknlp_display/VERSION
sparknlp_display/__init__.py
sparknlp_display/assertion.py
sparknlp_display/dep_updates.py
sparknlp_display/dependency_parser.py
sparknlp_display/entity_resolution.py
sparknlp_display/ner.py
sparknlp_display/re_updates.py
sparknlp_display/relation_extraction.py
sparknlp_display/retemp.py
sparknlp_display/style.css
sparknlp_display/style_utils.py
sparknlp_display/fonts/Lucida_Console.ttf
sparknlp_display/label_colors/ner.json
sparknlp_display/label_colors/relations.json
spark_nlp_display-4.4.dist-info/LICENSE
spark_nlp_display-4.4.dist-info/METADATA
spark_nlp_display-4.4.dist-info/WHEEL
spark_nlp_display-4.4.dist-info/top_level.txt
spark_nlp_display-4.4.dist-info/RECORD
