Metadata-Version: 2.1
Name: spark-nlp-display
Version: 4.4
Summary: Visualization package for Spark NLP
Home-page: http://nlp.johnsnowlabs.com
Author: John Snow Labs
Author-email: john@johnsnowlabs.com
License: UNKNOWN
Platform: UNKNOWN
Classifier: Programming Language :: Python :: 3
Classifier: Programming Language :: Python :: 2
Classifier: License :: OSI Approved :: Apache Software License
Classifier: Operating System :: OS Independent
Requires-Python: >=2.7
License-File: LICENSE
Requires-Dist: spark-nlp
Requires-Dist: ipython
Requires-Dist: svgwrite (==1.4)
Requires-Dist: pandas
Requires-Dist: numpy
